{
  "schemaVersion": 1,
  "itemCode": "4512785",
  "sections": [
    {
      "id": "prep",
      "title": "Forberedelser for oppdatering av heavy duty relé",
      "image": "devices/sentral_110290/images/help/4512785_help_1.png",
      "text": [
        "Først må du skru av dekselet på reléet for å få tilgang reset knappen.", 
        "Skruen finner du på undersiden av reléet. Bruk en stjerneskrutrekker for å skru ut skruen og ta av dekselet.",
        "Du har nå tilgang på reset knappen"
      ]
    },
    {
      "id": "update",
      "title": "Oppdatering av heavy duty relé",
      "image": "devices/sentral_110290/images/help/4512785_help_2.png",
      "text": [
        "Trykk på RESET knappen syv ganger, og deretter hold den inne på det åttende trykket til LED-lampen begynner å blinke raskt mellom blå og rød.", 
        "Dette indikerer at reléet er i paringsmodus og klar for oppdatering."
      ]
    }
  ]
}
